CHANGES.txt
LICENSE
MANIFEST.in
README.rst
requirements.txt
setup.py
LICENSES/JOBLIB_LICENSE
LICENSES/PANDAS_LICENSE
LICENSES/PYPRIND_LICENSE
LICENSES/PY_STRINGMATCHING_LICENSE
LICENSES/SIX_LICENSE
build_tools/cythonize.py
build_tools/move-conda-package.py
build_tools/appveyor/install.ps1
build_tools/appveyor/rm_rf.py
build_tools/appveyor/run_with_env.cmd
py_stringsimjoin/__init__.py
py_stringsimjoin.egg-info/PKG-INFO
py_stringsimjoin.egg-info/SOURCES.txt
py_stringsimjoin.egg-info/dependency_links.txt
py_stringsimjoin.egg-info/not-zip-safe
py_stringsimjoin.egg-info/requires.txt
py_stringsimjoin.egg-info/top_level.txt
py_stringsimjoin/datasets/__init__.py
py_stringsimjoin/datasets/base.py
py_stringsimjoin/datasets/data/books_table_A.csv.gz
py_stringsimjoin/datasets/data/books_table_B.csv.gz
py_stringsimjoin/datasets/data/person_table_A.csv
py_stringsimjoin/datasets/data/person_table_B.csv
py_stringsimjoin/filter/__init__.py
py_stringsimjoin/filter/filter.py
py_stringsimjoin/filter/filter_utils.py
py_stringsimjoin/filter/overlap_filter.py
py_stringsimjoin/filter/position_filter.py
py_stringsimjoin/filter/prefix_filter.py
py_stringsimjoin/filter/size_filter.py
py_stringsimjoin/filter/suffix_filter.py
py_stringsimjoin/index/__init__.py
py_stringsimjoin/index/index.py
py_stringsimjoin/index/inverted_index.py
py_stringsimjoin/index/inverted_index_cy.cpp
py_stringsimjoin/index/inverted_index_cy.pyx
py_stringsimjoin/index/position_index.py
py_stringsimjoin/index/position_index_cy.cpp
py_stringsimjoin/index/position_index_cy.pyx
py_stringsimjoin/index/prefix_index.py
py_stringsimjoin/index/size_index.py
py_stringsimjoin/join/__init__.py
py_stringsimjoin/join/cosine_join.py
py_stringsimjoin/join/cosine_join_cy.cpp
py_stringsimjoin/join/cosine_join_cy.pyx
py_stringsimjoin/join/cosine_join_py.py
py_stringsimjoin/join/dice_join.py
py_stringsimjoin/join/dice_join_cy.cpp
py_stringsimjoin/join/dice_join_cy.pyx
py_stringsimjoin/join/dice_join_py.py
py_stringsimjoin/join/disk_edit_distance_join.py
py_stringsimjoin/join/disk_edit_distance_join_cy.cpp
py_stringsimjoin/join/disk_edit_distance_join_cy.pyx
py_stringsimjoin/join/edit_distance_join.py
py_stringsimjoin/join/edit_distance_join_cy.cpp
